img2text_cli/__init__.py
img2text_cli/main.py
img2text_cli-0.1.7.dist-info/METADATA
img2text_cli-0.1.7.dist-info/WHEEL
img2text_cli-0.1.7.dist-info/entry_points.txt
img2text_cli-0.1.7.dist-info/RECORD
