Metadata-Version: 2.4
Name: img2text-cli
Version: 0.1.7
Summary: A CLI tool to extract text from images using OCR
Project-URL: Documentation, https://github.com/amanshaw4511/img2text-cli#readme
Project-URL: Homepage, https://github.com/amanshaw4511/img2text-cli
Project-URL: Issues, https://github.com/amanshaw4511/img2text-cli/issues
Project-URL: Repository, https://github.com/amanshaw4511/img2text-cli
Author-email: Aman Shaw <amanshaw4511@protonmail.com>
License: GPL-3.0
Keywords: cli,image,ocr,tesseract,text-extraction
Classifier: Development Status :: 4 - Beta
Classifier: Intended Audience :: Developers
Classifier: Intended Audience :: End Users/Desktop
Classifier: License :: OSI Approved :: GNU General Public License v3 (GPLv3)
Classifier: Operating System :: OS Independent
Classifier: Programming Language :: Python :: 3
Classifier: Programming Language :: Python :: 3.10
Classifier: Programming Language :: Python :: 3.11
Classifier: Programming Language :: Python :: 3.12
Classifier: Programming Language :: Python :: 3.13
Classifier: Topic :: Scientific/Engineering :: Image Processing
Classifier: Topic :: Text Processing
Classifier: Topic :: Utilities
Requires-Python: >=3.10
Requires-Dist: click>=8.2.1
Requires-Dist: pillow>=11.3.0
Requires-Dist: pyperclip>=1.9.0
Requires-Dist: pyperclipimg>=0.2.0
Requires-Dist: pytesseract>=0.3.13
